dedupkit/__init__.py
dedupkit/deduplicator.py
dedupkit/exceptions.py
dedupkit/validation.py
dedupkit/providers/__init__.py
dedupkit/providers/base.py
dedupkit/providers/embedding.py
dedupkit/providers/local.py
dedupkit/providers/openai.py
dedupkit/storage/__init__.py
dedupkit/storage/base.py
dedupkit/storage/memory.py
dedupkit/storage/postgres.py
dedupkit-0.1.2.dist-info/METADATA
dedupkit-0.1.2.dist-info/WHEEL
dedupkit-0.1.2.dist-info/licenses/LICENSE
dedupkit-0.1.2.dist-info/RECORD
