Metadata-Version: 2.4
Name: dedupkit
Version: 0.1.2
Summary: Semantic deduplication using embeddings
Author-email: Alexander Budanov <alex@apexbridge.tech>
License: MIT License
License-File: LICENSE
Requires-Python: >=3.10
Requires-Dist: numpy>=1.24.0
Provides-Extra: all
Requires-Dist: asyncpg>=0.29.0; extra == 'all'
Requires-Dist: openai>=1.10.0; extra == 'all'
Requires-Dist: pgvector>=0.2.4; extra == 'all'
Requires-Dist: sentence-transformers>=2.2.2; extra == 'all'
Provides-Extra: dev
Requires-Dist: mypy>=1.8.0; extra == 'dev'
Requires-Dist: pytest-asyncio>=0.23.0; extra == 'dev'
Requires-Dist: pytest>=7.4.0; extra == 'dev'
Requires-Dist: ruff>=0.1.0; extra == 'dev'
Provides-Extra: local
Requires-Dist: sentence-transformers>=2.2.2; extra == 'local'
Provides-Extra: openai
Requires-Dist: openai>=1.10.0; extra == 'openai'
Provides-Extra: postgres
Requires-Dist: asyncpg>=0.29.0; extra == 'postgres'
Requires-Dist: pgvector>=0.2.4; extra == 'postgres'
